README.rst
setup.py
comb/__init__.py
comb/combd.py
comb/main.py
comb/slot.py
comb.egg-info/PKG-INFO
comb.egg-info/SOURCES.txt
comb.egg-info/dependency_links.txt
comb.egg-info/entry_points.txt
comb.egg-info/requires.txt
comb.egg-info/top_level.txt
comb/demo/__init__.py
comb/demo/garbage.py
comb/demo/list.py
comb/demo/mongo.py
comb/demo/redis.py
comb/mq/__init__.py
comb/mq/mongo.py
comb/mq/mysql.py
comb/mq/redis.py