Metadata-Version: 1.0
Name: comb
Version: 0.9.9
Summary: A simple and high-performance framework for create concurrent program
Home-page: http://comb.readthdocs.org
Author: Wang WenPei
Author-email: wangwenpei@nextoa.com
License: http://opensource.org/licenses/MIT
Keywords: comb,slot,thread,framework,hook
Platform: UNKNOWN
